aiopath/__init__.py
aiopath/handle.py
aiopath/metadata.py
aiopath/path.py
aiopath/types.py
aiopath/wrap.py
aiopath-0.7.5.dist-info/LICENSE
aiopath-0.7.5.dist-info/METADATA
aiopath-0.7.5.dist-info/WHEEL
aiopath-0.7.5.dist-info/top_level.txt
aiopath-0.7.5.dist-info/zip-safe
aiopath-0.7.5.dist-info/RECORD
