Metadata-Version: 2.1
Name: aiopath
Version: 0.7.5
Summary: 📁 Async pathlib for Python
Home-page: https://github.com/AlexDeLorenzo
Author: Alex DeLorenzo <alex@alexdelorenzo.dev>
License: LGPL-3.0
Requires-Python: >=3.12
License-File: LICENSE
Requires-Dist: aiofile <4,>=3.8.8
Requires-Dist: anyio <5,>=4.0.0
Requires-Dist: typing-extensions >=3.10.0.0 ; python_version < "3.10"
